unretiredjs/__init__.py
unretiredjs/retirejs.py
unretiredjs/test_retirejs.py
unretiredjs/update_vulnerabilities.py
unretiredjs/vulnerabilities.py
unretiredjs-1.4.5.dist-info/licenses/LICENSE
unretiredjs-1.4.5.dist-info/METADATA
unretiredjs-1.4.5.dist-info/WHEEL
unretiredjs-1.4.5.dist-info/top_level.txt
unretiredjs-1.4.5.dist-info/RECORD
