Metadata-Version: 2.4
Name: unretiredjs
Version: 1.4.5
Summary: Python port of RetireJS - A tool to scan for vulnerabilities in JavaScript libraries
Author-email: Anand Kumar <anandseth444@gmail.com>
License: Apache-2.0
Project-URL: Homepage, https://github.com/Anandseth444/retirejslib
Project-URL: Changelog, https://github.com/Anandseth444/retirejslib/blob/main/CHANGELOG.md
Keywords: security,retirejs,python,vulnerability,javascript,scanner
Classifier: Development Status :: 4 - Beta
Classifier: Intended Audience :: Developers
Classifier: Programming Language :: Python :: 3
Classifier: Topic :: Security
Requires-Python: >=3.6
License-File: LICENSE
Requires-Dist: requests>=2.25.0
Dynamic: license-file
